[
  {
    "id": "1",
    "title": "Web Design",
    "category": "Web Design",
    "subTitle": "Stuff about the card",
    "cardBody": " Lorem ipsum, dolor sit",
    "projectImg": ""
  },
  {
    "id": "2",
    "title": "CSS Project",
    "category": "Css",
    "subTitle": "Stuff about the card",
    "cardBody": " Lorem ipsum, dolor.",
    "projectImg": ""
  },
  {
    "id": "3",
    "title": "React Project",
    "category": "React",
    "subTitle": "Stuff about the card",
    "cardBody": " Lorem ipsum, dolor sit amet ",
    "projectImg": ""
  },
  {
    "id": "4",
    "title": "Web Design",
    "category": "Web Design",
    "subTitle": "Stuff about the card",
    "cardBody": " Lorem ipsum, dolor ",
    "projectImg": ""
  },
  {
    "id": "5",
    "title": "CSS Project",
    "category": "Css",
    "subTitle": "Stuff about the card",
    "cardBody": " Lorem ipsum, dolor sit",
    "projectImg": ""
  },
  {
    "id": "6",
    "title": "React Project",
    "category": "React",
    "subTitle": "Stuff about the card",
    "cardBody": " Lorem ipsum, dolor ",
    "projectImg": ""
  }
]
